scr/__init__.py
NLP_classifier-0.1.dist-info/LICENSE
NLP_classifier-0.1.dist-info/METADATA
NLP_classifier-0.1.dist-info/WHEEL
NLP_classifier-0.1.dist-info/top_level.txt
NLP_classifier-0.1.dist-info/RECORD
