Metadata-Version: 2.1
Name: NLP-classifier
Version: 0.1
Summary: Vietnamese Newspapaper classifier
Home-page: https://github.com/Taiinguyenn139/NLPTextClassifier
Author: UNKNOWN
Author-email: taiinguyenn139@gmail.com
License: UNKNOWN
Platform: UNKNOWN
